etools/__init__.py
etools/async_http_client.py
etools/consts.py
etools/easync_http_client.py
etools/ehttp_client.py
etools/elk_record.py
etools/enum_meta.py
etools/http_client.py
etools/http_common.py
etools/singleton_meta.py
etools/utils.py
etools-0.0.16.dist-info/METADATA
etools-0.0.16.dist-info/WHEEL
etools-0.0.16.dist-info/top_level.txt
etools-0.0.16.dist-info/RECORD
