Metadata-Version: 2.1
Name: etools
Version: 0.0.16
Summary: some useful tools
Home-page: UNKNOWN
Author: sheng_xc
Author-email: sheng_xc@126.com
License: UNKNOWN
Platform: UNKNOWN
Classifier: Programming Language :: Python :: 3
Classifier: License :: OSI Approved :: MIT License
Classifier: Operating System :: OS Independent
Requires-Python: >=3.5
Requires-Dist: aiohttp (>=3.6.2)
Requires-Dist: requests (>=2.23.0)
